cythonimagetools/README.MD
cythonimagetools/__init__.py
cythonimagetools/requirements.txt
cythonimagetools/thirdparty.json
cythonimagetools-0.10.dist-info/LICENSE.rst
cythonimagetools-0.10.dist-info/METADATA
cythonimagetools-0.10.dist-info/WHEEL
cythonimagetools-0.10.dist-info/top_level.txt
cythonimagetools-0.10.dist-info/RECORD
