Metadata-Version: 2.1
Name: cythonimagetools
Version: 0.10
Summary: Provides functions (Cython - C) for color analysis in images, including finding unique colors, counting occurrences, and comparing images
Home-page: https://github.com/hansalemaos/cythonimagetools
Author: Johannes Fischer
Author-email: aulasparticularesdealemaosp@gmail.com
License: MIT
Keywords: rgb,Cython
Classifier: Development Status :: 4 - Beta
Classifier: Programming Language :: Python :: 3 :: Only
Classifier: Programming Language :: Python :: 3.10
Classifier: Topic :: Software Development :: Libraries :: Python Modules
Classifier: Topic :: Utilities
License-File: LICENSE.rst
Requires-Dist: Cython
Requires-Dist: a-cv-imwrite-imread-plus
Requires-Dist: numexpr
Requires-Dist: numpy
Requires-Dist: opencv-python
